nemweb/__init__.py
nemweb/nemfile_reader.py
nemweb/nemweb_current.py
nemweb/nemweb_sqlite.py
nemweb-0.1.dist-info/DESCRIPTION.rst
nemweb-0.1.dist-info/METADATA
nemweb-0.1.dist-info/RECORD
nemweb-0.1.dist-info/WHEEL
nemweb-0.1.dist-info/metadata.json
nemweb-0.1.dist-info/top_level.txt
