Metadata-Version: 2.0
Name: nemweb
Version: 0.1
Summary: newweb file handler
Home-page: UNKNOWN
Author: dylan
Author-email: dylan@opennem.org.au
License: MIT
Platform: UNKNOWN
Requires-Dist: pandas
Requires-Dist: requests
